{
  "build_entry_point": "",
  "need_generate_pdf": false,
  "docsets_to_publish": [
    {
      "docset_name": "OpenLocalizationOrg_HyperVTest_windowscontainers1",
      "build_source_folder": null,
      "build_output_subfolder": "olorg/hypervtest/virtualization/windowscontainers1",
      "build_entry_point": "op.ps1",
      "locale": "ja-jp",
      "version": 0,
      "open_to_public_contributors": false,
      "type_mapping": {
        "Conceptual": "Content",
        "ManagedReference": "Content"
      }
    },
    {
      "docset_name": "OpenLocalizationOrg_HyperVTest_community1",
      "build_source_folder": null,
      "build_output_subfolder": "olorg/hypervtest/virtualization/community1",
      "build_entry_point": "op.ps1",
      "locale": "ja-jp",
      "version": 0,
      "open_to_public_contributors": false,
      "type_mapping": {
        "Conceptual": "Content",
        "ManagedReference": "Content"
      }
    },
    {
      "docset_name": "OpenLocalizationOrg_HyperVTest_hyperv_on_windows1",
      "build_source_folder": null,
      "build_output_subfolder": "olorg/hypervtest/virtualization/hyperv_on_windows1",
      "build_entry_point": "op.ps1",
      "locale": "ja-jp",
      "version": 0,
      "open_to_public_contributors": false,
      "type_mapping": {
        "Conceptual": "Content",
        "ManagedReference": "Content"
      }
    }
  ],
  "notification_subscribers": null
}